src/__init__.py
src/env.py
src/main.py
src/mcp_server.py
src/tools.py
src/server_client/__init__.py
src/server_client/api_client.py
src/server_client/configuration.py
src/server_client/rest.py
src/server_client/api/__init__.py
src/server_client/api/collections_api.py
src/server_client/api/credentials_api.py
src/server_client/api/dcme_admin_api.py
src/server_client/api/dcme_api.py
src/server_client/api/dcme_connect_api.py
src/server_client/api/jobs_api.py
src/server_client/api/schedules_api.py
src/server_client/api/server_connections_api.py
src/server_client/api/subscriptions_api.py
src/server_client/api/user_groups_api.py
src/server_client/api/users_api.py
src/server_client/api/workflows_api.py
src/server_client/models/__init__.py
src/server_client/models/active_directory_object_view.py
src/server_client/models/ad_object.py
src/server_client/models/add_credentials_user_contract.py
src/server_client/models/add_credentials_user_group_contract.py
src/server_client/models/add_schedule_contract.py
src/server_client/models/add_server_connection_user_contract.py
src/server_client/models/add_server_connection_user_group_contract.py
src/server_client/models/add_user_contract.py
src/server_client/models/add_user_group_contract.py
src/server_client/models/add_workflow_contract.py
src/server_client/models/affected_schedule_view.py
src/server_client/models/app_value.py
src/server_client/models/asset_data_view.py
src/server_client/models/assets_view.py
src/server_client/models/change_users_subscription_contract.py
src/server_client/models/collection_user_view.py
src/server_client/models/collection_view.py
src/server_client/models/collections_permissions_view_contract.py
src/server_client/models/create_collection_contract.py
src/server_client/models/create_schedule_contract.py
src/server_client/models/create_subscription_contract.py
src/server_client/models/create_user_contract.py
src/server_client/models/create_user_group_contract.py
src/server_client/models/credentials_view.py
mcp_server_alteryx-0.2.22.dist-info/METADATA
mcp_server_alteryx-0.2.22.dist-info/WHEEL
mcp_server_alteryx-0.2.22.dist-info/entry_points.txt
mcp_server_alteryx-0.2.22.dist-info/licenses/LICENSE
mcp_server_alteryx-0.2.22.dist-info/RECORD
